processing/__init__.py
processing/combination.py
processing/transformation.py
utils/__init__.py
utils/io.py
utils/plot.py
ImageUnimedmarcosmvsfut-0.0.1.dist-info/METADATA
ImageUnimedmarcosmvsfut-0.0.1.dist-info/WHEEL
ImageUnimedmarcosmvsfut-0.0.1.dist-info/top_level.txt
ImageUnimedmarcosmvsfut-0.0.1.dist-info/RECORD
